specplot/__init__.py
specplot/fit.py
specplot/helper.py
specplot/plot.py
specplot-0.0.5.dist-info/LICENSE
specplot-0.0.5.dist-info/METADATA
specplot-0.0.5.dist-info/WHEEL
specplot-0.0.5.dist-info/RECORD
